routina/__init__.py
routina/cli.py
routina/decorators.py
routina/exceptions.py
routina/runner.py
routina/store.py
routina/timeutils.py
routina-0.1.1.dist-info/licenses/LICENSE
routina-0.1.1.dist-info/METADATA
routina-0.1.1.dist-info/WHEEL
routina-0.1.1.dist-info/entry_points.txt
routina-0.1.1.dist-info/top_level.txt
routina-0.1.1.dist-info/RECORD
