Metadata-Version: 2.4
Name: routina
Version: 0.1.1
Summary: A Python-native, time-aware function runner — like cron, but all in code
Author-email: Andrew Wade <andrew@example.com>
Maintainer-email: Andrew Wade <andrew@example.com>
License: MIT
Project-URL: Homepage, https://github.com/andrewwade/routina
Project-URL: Repository, https://github.com/andrewwade/routina
Project-URL: Documentation, https://github.com/andrewwade/routina#readme
Project-URL: Bug Tracker, https://github.com/andrewwade/routina/issues
Keywords: cron,scheduler,tasks,automation,time
Classifier: Development Status :: 4 - Beta
Classifier: Intended Audience :: Developers
Classifier: License :: OSI Approved :: MIT License
Classifier: Operating System :: OS Independent
Classifier: Programming Language :: Python :: 3
Classifier: Programming Language :: Python :: 3.8
Classifier: Programming Language :: Python :: 3.9
Classifier: Programming Language :: Python :: 3.10
Classifier: Programming Language :: Python :: 3.11
Classifier: Programming Language :: Python :: 3.12
Classifier: Topic :: Software Development :: Libraries :: Python Modules
Classifier: Topic :: System :: Systems Administration
Classifier: Topic :: Utilities
Requires-Python: >=3.8
License-File: LICENSE
Provides-Extra: dev
Requires-Dist: pytest>=7.0.0; extra == "dev"
Requires-Dist: pytest-cov>=4.0.0; extra == "dev"
Requires-Dist: black>=22.0.0; extra == "dev"
Requires-Dist: flake8>=5.0.0; extra == "dev"
Requires-Dist: mypy>=1.0.0; extra == "dev"
Requires-Dist: pre-commit>=2.20.0; extra == "dev"
Requires-Dist: build>=0.10.0; extra == "dev"
Requires-Dist: twine>=4.0.0; extra == "dev"
Requires-Dist: requests>=2.28.0; extra == "dev"
Dynamic: license-file
